{"d000.s001.t000": ["bapperl", "verhaltensregelwerk", "aufschrift", "adressetikett", "rfid-transponder", "label", "klebeetikett", "etiquette", "benimmregel", "beschriftung", "aufkleber", "verhaltensregel", "etikette", "etikett", "papperl", "bezeichnung"], "d000.s003.t000": ["trocken"], "d000.s006.t000": ["negation", "negieren"], "d000.s012.t000": ["absch\u00e4tzung", "evaluieren", "evaluationstheorie", "auswertung", "bewertung", "sch\u00e4tzung", "evaluierung", "evaluationsfunktionen", "pi mal daumen", "evaluation"], "d000.s014.t000": ["sich ereignen", "passieren", "geschehen", "auftauchen", "stattfinden passiere"], "d000.s016.t000": [], "d000.s018.t000": ["lebensweisheit", "weisheit"], "d000.s022.t000": ["endnote", "kommentar", "annotation", "anmerkung", "note", "fu\u00dfnotenapparat", "ton", "fu\u00dfnoten", "fu\u00dfnote", "anmerkungsapparat", "fussnote", "notiz"], "d000.s031.t000": ["prozent", "prozentsatz", "prozentualer anteil", "pct"], "d000.s032.t000": [], "d000.s038.t000": ["moment", "zeitpunkt", "augenblick", "sekunde"], "d000.s042.t000": ["strix", "waldk\u00e4uze"], "d000.s044.t000": ["einziehen", "revozieren", "widerrufen", "entziehen", "abschaffen", "aufk\u00fcndigen", "f\u00fcr ung\u00fcltig erkl\u00e4ren", "annullieren", "aufheben", "zur\u00fcckziehen", "aberkennen", "f\u00fcr nichtig erkl\u00e4ren", "ung\u00fcltig machen", "abbrechen", "r\u00fcckg\u00e4ngig machen", "zur\u00fccknehmen"], "d000.s045.t000": ["mechanische energie", "hilfsenergie", "energie"], "d000.s047.t000": ["armeedienst", "kriegsdienst", "wehrdienstleistender", "wehrdienst", "tsk", "dienst", "wehrpflicht", "pr\u00e4senzdiener", "teilstreitkraft", "grundwehrdiener", "milit\u00e4rdienst", "wehrdiener"], "d000.s049.t000": ["beistand", "hilfe", "humanit\u00e4re hilfe", "unterst\u00fctzung"], "d000.s050.t000": ["f\u00e4hrboot", "f\u00e4hrschiff", "wolke", "\u00fcberfuhr", "f\u00e4hre"], "d000.s051.t000": ["f\u00f6rdern", "unterst\u00fctzen", "helfen", "beistehen", "assistieren"], "d000.s057.t000": ["induktanz", "0,5", "induktivit\u00e4t", "ein halb", "h\u00e4lfte", "seite", "1/2", "spule"], "d000.s058.t000": ["handlungsempfehlung", "verwaltungsorgan", "board of directors", "orientierungshilfe", "anleitung", "richtungsweisung"], "d000.s062.t000": [], "d000.s063.t000": ["inspektion"], "d000.s069.t000": ["korbflechterei", "flechtkorb", "korb", "korbflechten", "flechtwerk"], "d000.s070.t000": ["sch\u00f6nheit"], "d000.s078.t000": ["markt", "weltmarkt", "g\u00fcterm\u00e4rkte", "marktplatz", "nachfrage", "anforderung"], "d000.s079.t000": ["zugleich", "zusammen", "zusammen z\u00e4me mitenand"], "d000.s080.t000": ["ei", "h\u00fchnerei"], "d000.s085.t000": ["heerf\u00fchrung", "landstreitkr\u00e4fte", "landarmee", "konstitutionelle armee", "heer"], "d000.s087.t000": ["gr\u00fcnspechte", "picus"], "d000.s088.t000": ["nebenwohnung", "ferienwohnung", "zweitwohnung", "ferienhaus", "nebenwohnsitz"], "d000.s090.t000": ["wechselstrom-anschluss", "stecker", "ableger", "steckdose", "netzsteckdose", "senkreis", "steckling"], "d000.s092.t000": ["tisch"], "d000.s099.t000": ["verlieren"], "d000.s100.t000": ["bolschewik", "bolshevik", "bolschewist", "bolschewiken", "bolschewiki", "bolschewisten"], "d000.s104.t000": ["motivieren"], "d000.s116.t000": ["philosophie der naturwissenschaften", "physik", "philosophie der naturwissenschaft", "naturphilosoph", "naturphilosophie"], "d000.s119.t000": ["entsperren", "er\u00f6ffnen", "entriegeln", "aufschlie\u00dfen"], "d000.s121.t000": ["kamm", "hahnenkamm", "b\u00fcrste"], "d000.s126.t000": ["\u017aar\u017ea\u015b", "halten"], "d000.s127.t000": ["region", "\u2295", "boden", "sol iii", "blauer planet", "erde", "\u2641", "l\u00e4nder", "grund", "land", "l\u00e4ndlicher raum", "landschaft", "l\u00e4ndliche siedlung", "erdboden", "erdkugel", "rural", "sol 3", "erdk\u00f6rper", "festland", "ruralit\u00e4t", "weltkugel", "welt"], "d000.s130.t000": [], "d000.s131.t000": [], "d000.s132.t000": ["feiner nebel", "dunst", "nebel"], "d000.s133.t000": ["umkehren", "umdrehen"], "d000.s136.t000": ["rotfichte", "gew\u00f6hnliche fichte", "rot-tanne", "rottanne", "picea excelsa", "picea", "fichten", "picea abies", "gemeine fichte", "fichte"], "d000.s137.t000": ["stock", "decke", "geschoss", "etage", "stockwerk", "gescho\u00df", "regime"], "d000.s142.t000": ["ost", "s\u00fcden", "ida", "osten", "international development association", "internationale entwicklungsorganisation", "himmelsrichtung"], "d000.s143.t000": ["rufaufbau", "anruf", "telefongespr\u00e4ch", "sprachanruf", "sprachkanal", "rede", "ansprache", "telefonat", "gespr\u00e4ch", "telefonverbindung", "vortrag", "telefonanruf", "w\u00e4hltasten"], "d000.s145.t000": ["\u2640", "weib", "feminin", "weibsperson", "dame", "frauenzimmer", "frauen", "weibliches geschlecht", "frau"], "d000.s148.t000": ["karikatur", "cartoon"], "d000.s150.t000": [], "d000.s152.t000": ["nehmen", "greifen", "ergreifen", "annehmen"], "d000.s153.t000": ["jahrmarkt"], "d000.s155.t000": ["\u00e4igeschaft", "eigenschaft", "qualit\u00e4t"], "d000.s156.t000": ["bildkontrast", "kontrast", "modulation"], "d000.s165.t000": ["gruppe", "gesellschaftliche gruppe", "zirkel", "gesellschaftsgruppe", "soziale gruppe"], "d000.s167.t000": ["\u03b4s", "entropie", "zufall"], "d000.s172.t000": [], "d000.s176.t000": ["erreichen"], "d000.s179.t000": ["soziale bewegung", "motilit\u00e4t", "hypomotilit\u00e4t", "fortbewegung", "hypermotilit\u00e4t", "bewegung", "motil", "lokomotion"], "d000.s181.t000": ["eigentum", "eigenschaften"], "d000.s182.t000": ["verachtung"], "d000.s185.t000": ["fu\u00dfbekleidung"], "d000.s191.t000": ["estrich", "s\u00f6ller", "spitzboden", "mansarde", "speicher", "boden", "trockenboden", "dachboden", "dachkammer", "dachgeschoss", "bodenkammer", "loftwohnung", "dachspeicher", "trockenspeicher", "dachraum"], "d000.s192.t000": ["elektrische leitf\u00e4higkeit", "schwierigkeit", "leiterwiderstand", "resistivit\u00e4t", "konduktivit\u00e4t", "problem", "problematisch", "widerstand", "elektrischer widerstand", "spezifischer leitwert", "impedanz", "behinderung", "probleme", "leitungswiderstand", "spezifischer widerstand", "problematik", "elektrischer leitwert", "leitf\u00e4higkeit", "spezifischer elektrischer widerstand", "problemkl\u00e4rung", "leitwert", "hindernis", "ohmscher widerstand"], "d000.s193.t000": ["hochchor", "gemischter chor", "altarraum", "obers", "rinde", "presbyterium", "gesangschor", "chor", "gerbrinde", "schale", "gleichstimmiger chor", "sprechchor", "chors\u00e4nger", "mulchrinde", "chorgesang", "borke", "chorraum", "sahne", "rindengewebe", "rahm", "baumrinde", "chorquadrat", "chorist", "volkschor", "ttbb"], "d000.s194.t000": ["brennstoffe", "brennmaterial", "brennstoff", "treibstoff"], "d000.s195.t000": ["tonart", "tonale musik", "tonalit\u00e4t"], "d000.s196.t000": ["schriftsystem", "brief", "schrift", "skriptum", "papierbrief", "schreiben", "handschrift", "skript", "sendschreiben", "musterbrief", "briefkopf"], "d000.s197.t000": ["druckgraphik", "originalgraphik", "grafik", "bildliche vorstellung", "druckgrafik", "graphik", "malerei", "rundbild", "abbild", "abbildung", "originalgrafik", "bild", "gem\u00e4lde", "malkunst", "panoramabild", "maler", "illustrierung", "panorama", "szene", "bebilderung", "kunstwerk", "imagery debate", "image", "darstellung"], "d000.s198.t000": ["kleiner teil", "kleines st\u00fcck", "splitter", "schiefer"], "d000.s199.t000": ["singstimme", "s\u00e4ngerin", "gesangsfach", "s\u00e4nger", "vokalisten", "vokalist", "gesang", "singen", "singapparat", "gesangsstil", "vokalpraxis", "gesangsapparat"], "d000.s200.t000": ["seiendes", "gesch\u00f6pf", "sein", "organismus", "das seiende", "gegebenes", "wesen", "lebewesen"], "d000.s203.t000": ["gemischter chor", "obers", "rinde", "gesangschor", "chor", "gerbrinde", "schale", "gleichstimmiger chor", "robert peel", "sprechchor", "chors\u00e4nger", "mulchrinde", "chorgesang", "borke", "sahne", "rindengewebe", "rahm", "baumrinde", "chorist", "volkschor", "ttbb"], "d000.s206.t000": ["\u00fcberreichen", "aush\u00e4ndigen", "abwerfen", "abgeben", "erbringen", "bringen", "reichen", "geben"], "d000.s209.t000": ["staatsb\u00fcrgerschaft", "b\u00fcrgerschaft", "staatsangeh\u00f6rigkeitsrecht", "staatsb\u00fcrgerrecht", "einb\u00fcrgerungspolitik", "staatsangeh\u00f6rigkeit", "doppelstaatsb\u00fcrgerschaft"], "d000.s210.t000": ["chance", "m\u00f6glichkeit", "gelegenheit"], "d000.s212.t000": ["rettung", "erl\u00f6sung", "erl\u00f6sungsreligion"], "d000.s216.t000": ["fahnenflucht"], "d000.s217.t000": ["dextrose", "st\u00e4rkezucker", "glycose", "glukose", "traubenzucker", "glucose"], "d000.s218.t000": ["philosophischer begriff", "philosophisches konzept", "begrifflichkeit", "auffassung", "bedeutungsbildung", "konstrukt", "konzept", "begriff", "begriffen"], "d000.s221.t000": ["suche", "lookup-tabelle"], "d000.s223.t000": ["kreuz", "\u2718"], "d000.s226.t000": ["summe", "anzahl", "total", "gesamt", "betrag", "menge"], "d000.s232.t000": ["bequemlichkeit", "ruhe", "friedensvertrag", "frieden", "scheinfriede", "friede", "friedensabkommen"], "d000.s233.t000": ["menschenrassen", "rassenkunde", "gro\u00dfrasse", "rassensystematik", "rassentheorie", "rasse", "rassenlehre", "rassentheoretiker", "rassenforschung", "rassenanthropologie", "rassentheorien", "gro\u00dfrassen"], "d000.s235.t000": ["kinetische energie", "geschwindigkeitsenergie", "bewegungsenergie"], "d000.s237.t000": [], "d000.s239.t000": ["theorie", "hypothesen", "hypothetisch", "hypothese"], "d000.s240.t000": ["riechstoffe", "duft", "geruchsstoff", "duftnote", "parf\u00fcm", "parfum", "aroma", "riechstoff", "duftstoff"], "d000.s242.t000": ["musikakademie", "hochschule f\u00fcr musik", "musikkonservatorium", "konservatorium", "h\u00f6here musikschule", "musikschule"], "d000.s249.t000": ["hinterfragen", "zweifel"], "d000.s254.t000": ["bild", "gem\u00e4lde"], "d000.s257.t000": ["anziehen"], "d000.s275.t000": ["brett", "planke"], "d000.s276.t000": ["komponieren", "abfassen", "kritzeln", "ver\u00f6ffentlichen", "zur feder greifen", "verfassen", "buchstabieren", "schreiben"], "d000.s281.t000": ["steigb\u00fcgel", "stapes"], "d000.s282.t000": ["herleiten", "folgern", "ableiten", "schlussfolgern"], "d000.s287.t000": ["bew\u00e4ssern", "irrigieren"], "d000.s288.t000": ["antik", "uralt"], "d000.s289.t000": ["cuculus canorus", "gemeiner kuckuck", "kuckuck"], "d000.s290.t000": ["rechtsdokument", "tat", "titel", "aktivit\u00e4t", "dokument", "ordnungswidrigkeit", "verbrechen", "beurkundet", "wirkung", "vergehen", "urkunde", "wirkungsintegral", "physikalische wirkung", "eigentumsnachweis"], "d000.s293.t000": ["schule", "akademie", "hochschule", "lehranstalt", "bildungsanstalt", "universit\u00e4t", "uni"], "d000.s294.t000": ["bass", "schildfu\u00df", "ba\u00df"], "d000.s296.t000": ["witwe", "witib", "witwer", "witfrau", "witmann", "wittib"], "d000.s299.t000": ["plagiator", "textplagiat", "pirat", "freibeutertum", "piratenangriff", "seer\u00e4uberei", "plagiarismus", "piraterie", "komplettplagiat", "seer\u00e4uber", "selbstplagiat", "seeraub", "freibeuterei", "\u00fcbersetzungsplagiat", "plagiat", "piratenakt", "flibustier"], "d000.s300.t000": ["skepsis", "skeptikerin", "skeptizismus", "skeptiker"], "d000.s301.t000": ["anschauen", "schauen", "sehen", "ansehen", "betrachten", "erblicken"], "d000.s302.t000": ["designerin", "hochbau-ingenieurin", "architektin", "architekt im praktikum", "designer", "hochbau-ingenieur", "entwerfer", "gestalterin", "gestalter", "planer", "architekt"], "d000.s303.t000": ["warten"], "d000.s304.t000": ["ordnung", "organisation", "organisatorisch", "ordo", "verein", "freiwillige vereinigung"], "d000.s306.t000": ["betonen", "gewichtung", "druck", "betonung", "akzent"], "d000.s307.t000": ["verlernen", "vergessen"], "d000.s309.t000": ["\u2764", "herzsymbol", "\u2661", "herzform", "r\u00fchrung", "affektion", "zuneigung", "freundschaftsliebe", "philia", "streicheleinheit", "herz"], "d000.s312.t000": ["portier", "concierge"], "d000.s316.t000": ["corpse", "leichnam", "leiche", "aas", "aase", "inhaltsverzeichnis", "botschaft", "kadaver", "nachricht", "mitteilung", "text", "steifer", "sterbliche \u00fcberreste", "inhalt"], "d000.s317.t000": ["erw\u00e4hnen"], "d000.s321.t000": ["adressat", "empf\u00e4nger", "rezipientin", "rezipient", "empf\u00e4ngerin", "adressatin"], "d000.s323.t000": ["kautschuk", "terpentinharz", "kolofonium", "harz", "colophonium", "geigenharz", "kolophonium", "bogenharz", "colofonium"], "d000.s326.t000": ["luftfilter", "wasserfilter", "filter"], "d000.s331.t000": [], "d000.s332.t000": ["szene"], "d000.s335.t000": ["biographie", "lebensbeschreibung", "leben", "biografie"], "d000.s337.t000": ["spiegelung"], "d000.s338.t000": ["verwundbarkeit", "sicherheitsmangel", "schw\u00e4che", "sicherheitsl\u00fccke", "gebrechlichkeit", "sicherheitsrisiko"], "d000.s339.t000": ["kreide-zeit", "kretazisch", "kreidezeit", "neokom", "kreide"], "d000.s340.t000": ["suffigierung", "postfix", "endsilbe", "affixum", "suffix", "suffixum", "anh\u00e4ngsilbe", "nachsilbe", "affix", "wortendung", "endung"], "d000.s343.t000": ["spielzug", "gangschaltung", "antriebsstrang", "gang", "drivetrain", "zug", "triebstrang"], "d000.s345.t000": ["verkn\u00fcpfen", "verknoten", "zusammenknoten", "binden", "verbinden", "sich vereinigen", "kn\u00fcpfen", "zusammenf\u00fcgen", "teilnehmen", "knoten"], "d000.s346.t000": ["st\u00e4rke", "intensit\u00e4t", "kraft"], "d000.s349.t000": ["wollen"], "d000.s351.t000": ["biographie", "lebensbeschreibung", "leben", "biografie", "lebende", "lebender"], "d000.s357.t000": ["spitze", "webspitze", "kl\u00f6ppelspitze"], "d000.s358.t000": ["rolle", "persona"], "d000.s360.t000": ["nick jr.", "birne", "r\u00fcbe"], "d000.s362.t000": [".", "stelle", "posten", "punkt", "schlusspunkt", "point", "grad"], "d000.s365.t000": ["interesse wecken", "fangen"], "d000.s368.t000": ["eingrenzen", "bestimmen"], "d000.s370.t000": ["indigenen amerikaner", "native americans", "amerikanische ureinwohner", "indianer in den usa", "inder", "indigene v\u00f6lker amerikas", "native american", "first people", "indianer", "ureinwohner amerikas"], "d000.s372.t000": ["tantallampe", "gl\u00fchfadenlampe", "metallfadenlampe", "elektrisches licht", "\u00f6llampe", "leuchte", "gl\u00fchlicht", "flamme", "feuerzeug", "leuchtmittel", "allgebrauchslampe", "a-lampe", "gl\u00fchlampe", "lampe", "luminaire", "gl\u00fchbirne"], "d000.s377.t000": ["autorit\u00e4t", "autorisierung", "erm\u00e4chtigung", "politische macht", "macht", "machtmittel", "vorherrschaft", "autorisiert", "kraft"], "d000.s378.t000": ["timbrologie", "sammeln von briefmarken", "philatelie", "timbrophilie", "briefmarkensammeln", "briefmarkenkunde", "briefmarkensammlung"], "d000.s381.t000": ["hautfl\u00fcgler", "hymenoptera", "hymenopteren"], "d000.s384.t000": ["ur\u00fcberlieferung", "weg", "brauch", "sitte", "gewohnheitsrecht", "tradition", "manier", "fasung", "herk\u00f6mmlich", "\u00fcberlieferung", "gewohnheit", "gepflogenheit", "angewohnheit", "mode", "traditionell", "stil"], "d000.s390.t000": ["beziehung", "partnerschaft"], "d000.s391.t000": ["fabula", "geschichte", "fabel", "plot", "handlung"], "d000.s403.t000": [], "d000.s405.t000": ["drechseln", "beschaffen", "empfangen", "verschaffen", "erhalten", "erwerben", "aufbringen", "besorgen", "beibringen", "bekommen", "erlangen", "sch\u00f6pfen"], "d000.s408.t000": ["stabsapotheker", "stabsveterin\u00e4r", "hauptmann", "stabshauptmann", "garnisonapotheker", "capitain"], "d000.s409.t000": ["corpse", "leichnam", "bedeutung", "leiche", "aas", "aase", "inhaltsverzeichnis", "kadaver", "text", "steifer", "sterbliche \u00fcberreste", "inhalt"], "d000.s411.t000": ["quell", "quelle", "wasserquelle"], "d000.s416.t000": ["bewerbung", "antrag"], "d000.s419.t000": ["ungeheuer", "untier", "unget\u00fcm", "monster", "monstrum"], "d000.s422.t000": ["reichtum", "verm\u00f6gen"], "d000.s423.t000": ["kurz"], "d000.s425.t000": ["leiten", "beaufsichtigen", "verwalten"], "d000.s432.t000": ["tomate", "lycopersicon esculentum cerasiforme", "cherrytomaten", "solanum lycopersicum", "lycopersicon esculentum", "fleischtomate", "paradeiser", "peruanischer apfel", "cherry-tomate", "pomidore", "kirschtomate", "goldapfel", "cherrytomate", "cocktailtomate", "wolfspfirsich"], "d000.s433.t000": ["beschaffen", "empfangen", "verschaffen", "erhalten", "erwerben", "aufbringen", "besorgen", "beibringen", "bekommen", "ankommen", "erlangen", "sch\u00f6pfen"], "d000.s434.t000": ["antifeminismus", "hurra-patriotismus", "chauvinist", "hurrapatriotismus", "chauvi", "chauvinismus", "chauvinistisch"], "d000.s438.t000": ["new wave", "vorhut", "new-wave", "avantgarde", "spitze", "avantgardismus", "avantgardist", "avant garde", "avantgardistisch", "avant-garde"], "d000.s440.t000": ["applikationsprogramm", "computerprogramm", "softwareprogramm", "programm", "computerbefehl"], "d000.s441.t000": ["hinschied", "sensenmann", "exitus", "ableben", "gevatter", "tod"], "d000.s443.t000": ["gartenanlage", "garten", "g\u00e4rtnern", "vorgarten"], "d000.s445.t000": [], "d000.s447.t000": ["renken", "coregonen", "reinanken", "mar\u00e4nen felch kilch", "schn\u00e4pel"], "d000.s449.t000": ["universit\u00e4t", "uni", "akademie", "akademie akademische einrichtung"], "d000.s450.t000": ["spielfilm", "kinofilm", "arthouse film", "film"], "d000.s455.t000": ["steuerrad"], "d000.s457.t000": ["finden", "entdeckung"], "d000.s458.t000": ["kurs", "klasse", "kategorie", "classis", "schulklasse"], "d000.s462.t000": ["ehrenwort", "wort der ehre", "zusicherung"], "d000.s469.t000": ["tats\u00e4chlich", "wirklich", "eigentlich aigetli"], "d000.s473.t000": ["beschaffen", "verschaffen", "erwerben", "aufbringen", "besorgen", "beibringen", "erlangen", "sch\u00f6pfen"], "d000.s474.t000": ["sitzung"], "d000.s475.t000": ["absatz"], "d000.s476.t000": ["trinken", "saufen", "schlabbern"], "d000.s477.t000": ["\u00e4thylalkohol", "alkohol", "ethanol", "ethylalkohol", "alkohole", "spiritus", "\u00e4thanol", "weingeist", "alkanol"], "d000.s485.t000": ["hungerrevolte", "hungerkatastrophe", "nahrungskrise", "hungernot", "hungerkrise", "hunger", "hungersnot"], "d000.s486.t000": ["region", "gegend", "raum", "gebiet"], "d000.s488.t000": ["beschaffungsauftrag", "normalbestellung", "gerichtsurteil", "bestellung", "bestellnummer", "urteil", "order", "gehei\u00df", "einkaufsauftrag", "bestellanforderung", "befehl", "purchase order"], "d000.s490.t000": ["wald", "driver", "forst", "w\u00e4lder", "busch", "holz"], "d000.s500.t000": ["intervall", "offenes intervall", "intervallschreibweise", "abgeschlossenes intervall", "geschlossenes intervall", "intervallgrenze"], "d000.s501.t000": ["gefallen"], "d000.s505.t000": ["erleichtern", "mildern", "abschw\u00e4chen", "lindern"], "d000.s506.t000": ["streicheln", "liebkosen"], "d000.s511.t000": ["drechseln", "bekommen", "empfangen", "ankommen", "erhalten"], "d000.s516.t000": ["politische philosophie", "politikphilosophie", "ideologie", "weltanschauung"], "d000.s518.t000": ["aufenthalt"], "d000.s520.t000": ["maustreiber", "druckertreiber", "windows driver model", "treibersoftware", "treibermodell", "generischer treiber", "treiber", "klassentreiber", "ger\u00e4tetreiber"], "d000.s521.t000": ["buech", "boch", "buch"], "d000.s523.t000": ["ausmisten", "kuhmist", "mist", "pferdemist", "d\u00fcnger", "miststock", "stallmist"], "d000.s525.t000": ["korb"], "d000.s527.t000": ["flagge", "f\u00e2ne", "fahne"], "d000.s528.t000": ["tod", "untergang"], "d000.s530.t000": ["negation", "negieren"], "d000.s531.t000": ["organisation", "staatskirche", "staatsreligion", "offizielle religion"], "d000.s532.t000": ["scheibe", "kreisscheibe", "kreisfl\u00e4che"], "d000.s535.t000": ["alkoholismus"], "d000.s539.t000": ["treue", "akkuratesse", "\u00e4u\u00dfere genauigkeit", "innere genauigkeit", "wahrheit", "\u00e4ussere genauigkeit", "pr\u00e4zision", "genauigkeit", "wiederholgenauigkeit", "absolute genauigkeit"], "d000.s542.t000": ["figur", "schachstein", "schachfigur"], "d000.s544.t000": ["kreiszylinder", "zylindermantel", "zylinder", "hoher hut", "zylinderhut", "zylindrisch"], "d000.s548.t000": ["gelegen", "g\u00fcnstig", "einfach", "bequem", "passend", "genehm", "leicht", "praktisch"], "d000.s549.t000": ["verlust"], "d000.s550.t000": ["tag", "heller tag", "tageszeit", "tageslicht"], "d000.s553.t000": ["region", "gegend", "raum", "gebiet"], "d000.s555.t000": ["haben haa", "sein", "sein sich befinden", "passieren", "sein stattfinden", "bestehen", "existieren", "geschehen"], "d000.s558.t000": ["gesamtwirtschaftliche ersparnis", "nationale ersparnis", "ersparnis", "private ersparnis", "\u00f6ffentliche ersparnis", "sparen", "sparer"], "d000.s563.t000": ["sorte", "cultivar", "kulturvariet\u00e4t", "cultivare", "kultivar", "kultivare"], "d000.s564.t000": ["sturm"], "d000.s567.t000": ["schlachtruf", "kampfruf", "schlachtgeschrei", "feldgeschrei", "schrei"], "d000.s568.t000": ["gemeinsam"], "d000.s569.t000": ["haben haa", "sein", "passieren", "sein stattfinden", "sein sich befinden", "geschehen"], "d000.s573.t000": ["hautkrankheiten", "streichgarn", "wollstoffe", "dermatose", "hautkrankheit", "bulla", "reine schurwolle", "blase", "wolle", "hauterkrankung", "merinowolle", "kurkwolle"], "d000.s577.t000": ["agens", "agent", "telefonist"], "d000.s578.t000": ["flo\u00df", "wolke"], "d000.s579.t000": ["liebesspiel", "paarung", "kopulation", "verkehr", "koitus", "geschlechtsverkehr", "sexualkontakt", "geschlechtsakt", "akt", "kohabitation", "beischlaf", "sex", "begattung", "liebesakt"], "d000.s581.t000": ["biegung"], "d000.s583.t000": ["schreibtafel", "wandtafel", "tafel", "schultafel"], "d000.s587.t000": ["verzeichnis", "index", "register"], "d000.s589.t000": ["einladen \u012bnladen inlad\u014dn", "einladen"], "d000.s590.t000": ["hass", "ha\u00df", "zorn"], "d000.s593.t000": ["strophenform", "strophe"], "d000.s595.t000": ["zaunk\u00f6nig", "schneek\u00f6nig", "troglodytes troglodytes", "troglodytes hiemalis"], "d000.s600.t000": ["aktivit\u00e4tskoeffizient", "t\u00e4tigkeit", "aktivit\u00e4t", "wirkung", "chemische aktivit\u00e4t", "action", "wirkungsintegral", "physikalische wirkung"], "d000.s601.t000": ["monarchist", "royalismus", "monarchisten", "monarchismus"], "d000.s604.t000": [], "d000.s605.t000": ["speicherregister", "verzeichnis", "index", "register", "protokoll", "prozessorregister", "beleg"], "d000.s619.t000": ["kochlea", "schnecken", "schnecke", "geh\u00f6rschnecke", "gastropode", "bauchf\u00fc\u00dfer", "scala tympani", "cochlea", "scala vestibuli", "h\u00f6rschnecke", "gastropoda"], "d000.s620.t000": ["stimmen", "w\u00e4hlen"], "d000.s630.t000": ["lotus", "lotuswurzel", "lotusgew\u00e4chse", "lotusblume", "nelumbonaceae", "nelumbo", "lotusblumen", "lotosblumen", "lotosgew\u00e4chse"], "d000.s631.t000": ["m\u00f6nchstum", "bruder", "m\u00f6nch"], "d000.s633.t000": ["job", "ort", "beruf", "stelle", "platz", "geographische lage", "besch\u00e4ftigung", "position", "koordinate", "anstellung", "standort", "arbeit", "prueff", "stellung"], "d000.s634.t000": ["bullig", "kr\u00e4ftig"], "d000.s635.t000": ["therapie", "behandlung", "therapeutik", "therapieoption", "therapeutisch", "medizinische behandlung", "therapieresistenz", "selbsttherapie"], "d000.s637.t000": ["rufaufbau", "sprechen", "anruf", "telefongespr\u00e4ch", "sprachanruf", "sprachkanal", "gesprochene sprache", "m\u00fcndliche kommunikation", "telefonat", "gespr\u00e4ch", "telefonverbindung", "sprache", "telefonanruf", "w\u00e4hltasten", "gesprochenes"], "d000.s643.t000": ["jux", "marotte", "saft", "spa\u00df", "eskapade", "kasperei", "gag", "albernheit", "ulk", "narretei", "witz", "joke", "posse", "clue", "streich", "alberei", "klamauk", "scherz", "laune", "witzlos", "kapriole", "m\u00e4tzchen", "gekasper"], "d000.s646.t000": ["fahren"], "d000.s652.t000": ["frieden", "scheinfriede", "friede", "friedensvertrag", "friedensabkommen"], "d000.s653.t000": ["messger\u00e4t", "meter", "dimension", "ma\u00df"], "d000.s654.t000": ["behalten", "aufheben"], "d000.s655.t000": ["argument", "parameter", "kenngr\u00f6\u00dfe", "formaler parameter", "parameter\u00fcbergabe", "funktionsparameter", "type-hinting"], "d000.s659.t000": ["nehmen", "lesen l\u00e4se"], "d000.s660.t000": ["knopf", "schaltfl\u00e4che", "taste", "figur", "schachstein", "schachfigur", "drucktaster"], "d000.s666.t000": ["schneefall", "schneedecke", "schnee"], "d000.s668.t000": ["steinschleuder", "schleuder", "fustibal"], "d000.s670.t000": ["reich", "regnum", "staat"], "d000.s674.t000": ["kern", "herz"], "d000.s675.t000": ["fabrikgeb\u00e4ude", "papierm\u00fchle", "produktionsst\u00e4tte", "werk", "fabrik", "manufaktur"], "d000.s677.t000": ["baum"], "d000.s683.t000": [], "d000.s684.t000": ["verkn\u00fcpfung", "verkettung", "glied", "aneinanderreihung", "konkatenation", "kette"], "d000.s685.t000": ["prozess", "mentaler prozess"], "d000.s686.t000": ["zahlungsmittel", "kohle", "knete", "geld", "zaster", "schotter", "moneten"], "d000.s690.t000": ["spatz", "haussperling", "passer", "hausspatz", "sperling"], "d000.s691.t000": ["bewegungsgesetze", "bewegung", "hypomotilit\u00e4t", "fortbewegung", "hypermotilit\u00e4t", "bewegungsgesetz", "motilit\u00e4t", "ungleichf\u00f6rmige bewegung", "motil", "lokomotion"], "d000.s694.t000": ["glaubenssystem", "glaubenswissen", "glaube", "annahme", "glauben", "meinung"], "d000.s696.t000": ["vogelpenis", "schwanz", "pimmel", "vorderbein", "extremit\u00e4ten", "m\u00e4nnliches glied", "mitglied", "l\u00fcmmel", "vorderextremit\u00e4t", "hinterbein", "pipimann", "gliedma\u00dfe", "penis", "corpus penis", "piepmatz", "gliedma\u00dfen", "glied", "vordergliedma\u00dfe", "akropodium", "zygopodium", "penis der s\u00e4ugetiere", "basipodium", "gliedmassen", "k\u00f6rperglied", "metapodium", "extremit\u00e4t", "ger\u00e4t", "stylopodium", "arsch", "zipfel", "autopodium", "teil", "penis der v\u00f6gel", "zonoskelett", "willy", "penisschaft"], "d000.s698.t000": ["sula"], "d000.s705.t000": ["schloss"], "d000.s706.t000": ["\u00e4thylalkohol", "alkohol", "ethanol", "ethylalkohol", "spiritus", "weingeist", "\u00e4thanol"], "d000.s708.t000": [], "d000.s712.t000": ["f\u00fchlen", "kennen w\u00fcsse", "sp\u00fcren"], "d000.s713.t000": ["unterhalten", "klatschen", "kl\u00f6nen", "schwatzen", "plaudern", "sich unterhalten"], "d000.s715.t000": ["grube", "loch"], "d000.s716.t000": ["schampu", "haarwaschmittel", "schampon", "shampoo", "schampun"], "d000.s721.t000": ["anwendungsprogramm", "arbeitssoftware", "anwendungs-software", "desktop-app", "anwenderprogramm", "application", "anwendersoftware", "softwareanwendung", "anwendung", "anwendungsprogramme", "desktopanwendung", "applikation", "app", "anwendungssoftware", "desktop-anwendung"], "d000.s727.t000": ["silo", "fahrsilo", "getreidesilo", "hochsilo"], "d000.s729.t000": ["bowlingbahn", "schmei\u00df", "bowling"], "d000.s732.t000": ["schmied", "grobschmiedin", "grobschmied"], "d000.s734.t000": ["ladestreifen", "laderahmen", "ladeclips", "munitionslager", "ladeclip", "magazin"], "d000.s738.t000": ["queckenwurzel", "hystrix", "haargerste", "quecken", "elymus"], "d000.s742.t000": ["tiergattung", "genus", "pflanzengattung", "familie", "familia", "gattung", "pflanzenfamilie"], "d000.s744.t000": ["historien des herodot", "geschichte", "herodots historien", "historien", "erz\u00e4hlung", "chronik"], "d000.s749.t000": ["park", "parkanlage", "parklandschaft", "volkspark"], "d000.s750.t000": ["wiege", "g\u00fbtsche"], "d000.s752.t000": ["wien"], "d000.s753.t000": ["geben", "\u00fcberreichen", "aush\u00e4ndigen", "reichen", "abgeben"], "d000.s755.t000": ["gestalt", "zustand", "form"], "d000.s762.t000": ["marionette", "handpuppe"], "d000.s767.t000": ["potentialdifferenz", "elektrisches potential", "mechanische spannung", "elektrische spannung", "spannung"], "d000.s769.t000": ["drechseln", "bekommen", "empfangen", "ankommen", "erhalten"], "d000.s770.t000": ["motiv"], "d000.s772.t000": ["rubus"], "d000.s776.t000": ["anfangen", "starten", "beginnen"], "d000.s777.t000": ["studieren", "lernen", "erforschen"], "d000.s778.t000": ["ver\u00f6ffentlichen", "kritzeln", "zur feder greifen", "buchstabieren", "schreiben"], "d000.s781.t000": ["klubhaus", "verein", "freiwillige vereinigung"], "d000.s782.t000": ["fahrt", "spielzug", "gang", "reise", "zug"], "d000.s784.t000": ["untere extremit\u00e4t", "fu\u00df", "bein", "versfu\u00df", "beine"], "d000.s785.t000": ["region", "\u2295", "sol iii", "blauer planet", "erde", "\u2641", "bundesstaat in mexiko", "land der bundesrepublik deutschland", "land", "landschaft", "l\u00e4ndlicher raum", "l\u00e4ndliche siedlung", "bundesland", "erdkugel", "rural", "sol 3", "nationalstaat", "erdk\u00f6rper", "ruralit\u00e4t", "nation", "staat", "weltkugel", "verwaltungseinheit von mexiko", "welt"], "d000.s786.t000": ["essen", "viktualien", "nahrungsmittel", "lebensmittel", "n\u00e4hrstoff", "nahrung", "speise", "n\u00e4hrstoffe"], "d000.s794.t000": ["beklagte", "verd\u00e4chtiger", "verd\u00e4chtige", "angeklagte", "beklagter", "klagegegner"], "d000.s795.t000": ["verbot"], "d000.s805.t000": ["beklagen", "wehklagen", "klagen"], "d000.s809.t000": ["ecke", "winkelabstand", "drehwinkel", "winkeldistanz", "ebener winkel", "winkelgesetze", "winkel"], "d000.s810.t000": ["gericht", "gerichtshof", "verpflichtung", "versprechen"], "d000.s811.t000": ["kennen w\u00fcsse"], "d000.s812.t000": ["hauszwiebel", "zwiebellauch", "zwiebel", "zwiebeln", "gartenzwiebel", "luftzwiebel", "etagenzwiebel", "gemeine zwiebel", "allium cepa", "sommerzwiebel", "zwiebelpflanze", "k\u00fcchenzwiebel", "speisezwiebel", "blumenzwiebel"], "d000.s813.t000": ["beabsichtigen", "sinnieren", "intendieren", "vorhaben", "nachdenken", "\u00fcberlegen", "reflektieren", "nachsinnen", "denken", "gr\u00fcbeln", "sinnen"], "d000.s814.t000": ["hochchor", "gemischter chor", "altarraum", "rinde", "presbyterium", "gesangschor", "chorist", "chor", "gerbrinde", "schale", "gleichstimmiger chor", "robert peel", "sprechchor", "chors\u00e4nger", "mulchrinde", "borke", "chorraum", "rindengewebe", "baumrinde", "chorquadrat", "chorgesang", "volkschor", "ttbb"], "d000.s818.t000": ["\u017aar\u017ea\u015b", "halten"], "d000.s824.t000": ["muskelmagen", "kaumagen"], "d000.s829.t000": [], "d000.s831.t000": ["punktpunktpunkt", "hellip", "punkt punkt punkt", "\u2026", "satzellipse", "ellipse", "\u03ad\u03bb\u03bb\u03b5\u03b9\u03c8\u03b9\u03c2", "...", "auslassungspunkte"], "d000.s832.t000": ["kannibalismus", "kannibalen", "endokannibalismus", "androphagie", "gynophagia", "kannibale", "exokannibalismus", "gynophagie"], "d000.s833.t000": ["wei\u00dfe", "wei\u00df", "wei\u00dfgrad"], "d000.s834.t000": ["natur", "umwelt"], "d000.s836.t000": ["lederwaren", "leder"], "d000.s837.t000": ["sch\u00e4rfen"], "d000.s838.t000": ["cementum", "zahnzement", "wurzelzement", "zement"], "d000.s845.t000": ["wanze"], "d000.s850.t000": ["gesellschaftliche klasse", "klasse", "gesellschaftsklasse", "gesellschaftsschicht", "kurs", "schicht", "soziale klasse", "kategorie", "klassen\u00fcberwindung", "classis"], "d000.s851.t000": ["schlacht", "kampf"], "d000.s852.t000": ["lack", "firnis"], "d000.s853.t000": ["funkenflug", "funke"], "d000.s856.t000": ["wettbewerb"], "d000.s858.t000": ["herunterladen", "downloaden", "ziehen", "anziehen"], "d000.s859.t000": ["reliquiarkrone", "zahnkrone", "krone"], "d000.s862.t000": ["grundgebete", "gebet", "gebetsarten"], "d000.s863.t000": ["menschlichkeit", "humanit\u00e4t"], "d000.s865.t000": ["komponieren", "abfassen", "kritzeln", "zur feder greifen", "verfassen", "buchstabieren", "schreiben"], "d000.s866.t000": ["gestik", "geste", "handgeste"], "d000.s868.t000": ["gro\u00df", "hoch"], "d000.s870.t000": ["unmoralisch", "moralisch", "unmoral", "sittenlehre", "moral"], "d000.s871.t000": ["zutreter", "sch\u00e4fchen", "lamm", "j\u00e4hrling"], "d000.s873.t000": ["flu\u00dfbett", "bachbett", "gew\u00e4sserbett", "flussbett", "flussbett, bachbett"], "d000.s877.t000": ["schnelligkeit", "geschwindigkeit", "umfanggeschwindigkeit", "geschwindigkeitsvektor", "umfangsgeschwindigkeit", "rate", "bahngeschwindigkeit", "fahrgeschwindigkeit", "momentangeschwindigkeit"], "d000.s879.t000": ["sammelrezension", "kritik", "buchrezension", "literaturwissenschaft", "literaturkritik", "buchkritik", "literaturbesprechung", "literaturrezension", "buchbesprechung"], "d000.s880.t000": ["preisentwicklung", "preiserh\u00f6hung", "ladenverkaufspreis", "marktpreise", "\u00f6konomischer wert", "schaden", "faktorpreis", "verkaufspreis", "g\u00fcterpreis", "gro\u00dfe deflation", "wert", "absatzpreis", "preis"], "d000.s884.t000": ["wei\u00dfe vaseline", "vaselinum album", "vaselin", "wei\u00dfes petrolatum", "wei\u00dfes vaselin", "vaseline", "petrolatum"], "d000.s887.t000": ["einen satz machen", "h\u00fcpfen", "springen"], "d000.s888.t000": ["politische wahl", "wahl"], "d000.s889.t000": ["zugleich", "zusammen", "zusammen z\u00e4me mitenand"], "d000.s890.t000": ["oberkiefer", "kinnbacke", "kiefer", "kinnbacken", "kieferknochen"], "d000.s893.t000": ["profil"], "d000.s894.t000": ["gemein", "generalisierung", "induktionsschluss", "generalsierung", "induktionslogik", "verallgemeinerung", "induktion", "induktionsprinzip", "induktiver schluss"], "d000.s896.t000": ["fachdisziplin", "chemische substanz", "stoff", "chemikalie", "chemische industrie", "einzelwissenschaft", "schulfach", "chemische k\u00f6rper", "unterrichtsfach", "fachwissenschaft", "fach", "lehrfach", "studienfach", "disziplin", "chemischer stoff", "feld", "gebiet", "bereich"], "d000.s902.t000": ["kongress", "kongress der vereinigten staaten"], "d000.s904.t000": ["ankommen", "kommen"], "d000.s913.t000": ["schiffshafen", "\u00f6lhafen", "hafenanlage", "hafen", "kontainerhafen"], "d000.s917.t000": [], "d000.s920.t000": ["gras"], "d000.s925.t000": ["vergessen"], "d000.s927.t000": ["einbruch der dunkelheit", "d\u00e4mmerung", "morgend\u00e4mmerung", "zivile d\u00e4mmerung", "d\u00e4mmerungsfarben", "astronomische d\u00e4mmerung", "einbruch der nacht", "zwielicht", "abendd\u00e4mmerung", "nautische d\u00e4mmerung"], "d000.s928.t000": ["doofkopf", "idiot", "bl\u00f6dian", "dumpfbacke", "schwachmat", "dummbratze", "strohkopf", "schwachkopf", "kamel", "einfaltspinsel", "tor", "dummkopf", "holzkopf", "spatzengehirn", "tropf", "dumme gans", "spaten", "l\u00f6\u00f6l", "doofi", "n\u00e4rrin", "hohlkopf", "dummerjan", "d\u00f6skopp", "schafskopf", "honk", "depp", "t\u00f6rin", "hirni", "mondkalb", "armleuchter", "flachwichser", "hornochse", "stiesel", "hofn\u00e4rrin", "dummer mensch", "spatzenhirn", "gimpel", "trottel", "dummerchen", "simpel", "bl\u00f6dmann", "kindskopf", "rindvieh", "narr", "vollpfosten", "vollhonk", "d\u00e4mlack", "esel", "ein dummer mensch", "hofnarr"], "d000.s929.t000": ["konvent", "kloster", "abtei", "kl\u00f6ster"], "d000.s936.t000": ["schachpatt", "pattsituation", "pattstellung", "s\u00fcnde", "pat", "patt"], "d000.s939.t000": ["bildhauerei"], "d000.s943.t000": ["gegenlied", "parodien", "stimmparodie", "extravaganza", "parodist", "parodie", "parodistisch", "victorian burlesque", "pasquino"], "d000.s949.t000": ["anfrage"], "d000.s951.t000": ["zeile", "datensatz", "linie", "taktstrich"], "d000.s959.t000": ["haus"], "d000.s960.t000": ["aromatizit\u00e4t", "aromatische cyclen", "aromatischer ring", "aromaten", "aromatische verbindungen", "aromatische verbindung"], "d000.s968.t000": ["medikamentation", "medikamente", "therapeutikum", "arznei", "medikament", "arzenei", "pharmazeutika", "pharmakotherapie", "therapeutika", "arzneimittel", "pharmazeutikum", "medikation"], "d000.s969.t000": ["andenken", "relikt", "mitbringsel", "erinnerung", "erinnerungsst\u00fcck", "reisemitbringsel", "souvenir", "liebgewonnenes", "reiseandenken"], "d000.s974.t000": ["schachmatt"], "d000.s978.t000": ["bezahlen", "zahlen"], "d000.s979.t000": ["roman"], "d000.s981.t000": ["bleistift"], "d000.s983.t000": [], "d000.s986.t000": ["vorstellen", "vorhaben", "einbilden", "sich vorstellen", "beabsichtigen", "denken", "intendieren"], "d000.s989.t000": ["druckgraphik", "originalgraphik", "grafik", "bildliche vorstellung", "druckgrafik", "graphik", "malerei", "abbild", "abbildung", "abbildtheorie", "originalgrafik", "bild", "gem\u00e4lde", "zeichnung", "malkunst", "maler", "illustrierung", "bebilderung", "kunstwerk", "imagery debate", "image", "darstellung"], "d000.s993.t000": ["theater", "dramaturgie", "theaterst\u00fcck"], "d000.s994.t000": ["signifikat", "sinn"], "d000.s998.t000": ["tag", "solartag", "sonnentag"], "d000.s1000.t000": ["bestickung", "deichbau", "schutzdamm", "deich", "seedeich", "graben", "quercus robur", "stieleiche", "quercus pendunculata", "ringdeich", "sommereiche", "sommer-eiche", "stiel-eiche"], "d000.s1001.t000": ["erreichen"], "d000.s1014.t000": ["maler"], "d000.s1020.t000": ["herr"], "d000.s1021.t000": ["flanke"], "d000.s1024.t000": ["zahlzeichen", "anzahl", "dezimal", "ziffer", "zahl"], "d000.s1033.t000": ["ehegatte", "m\u00e4nner", "gemahl", "kerl", "ehegemahl", "ehegespons", "herr", "mannsperson", "mann", "ehegesponst", "gatte", "mannsbild", "ehepartner", "ehemann"], "d000.s1035.t000": ["genie\u00dfen", "sich erfreuen an"], "d000.s1039.t000": ["revolution\u00e4rin", "revolution\u00e4r"], "d000.s1041.t000": ["freundschaft", "kameradschaft", "freunde"], "d000.s1043.t000": ["fletsche", "zwille", "steinschleuder", "fustibal", "schleuder", "katschi"], "d000.s1044.t000": ["speisesalz", "gastrointestinaltrakt", "eingeweide", "intestinum", "verdauungstrakt", "magen-darm-trakt", "darm", "dickdarm", "kochsalz", "intestinal", "tafelsalz", "magen-darm-kanal", "verdauungsapparat", "ged\u00e4rme", "salz"], "d000.s1045.t000": ["teigwaren", "nudeln", "nudelgericht", "pasta"], "d000.s1047.t000": ["fl\u00fcgel", "geb\u00e4udefl\u00fcgel", "nebengeb\u00e4ude", "geb\u00e4udetrakt", "anbau"], "d000.s1051.t000": ["wahl", "alternative", "entscheidung", "auswahl", "option"], "d000.s1052.t000": ["sonnenlicht", "sonnenstrahlung", "sonnenstrahl", "sonne", "solare einstrahlung", "sonnenschein", "sonnenglast", "solarspektrum", "fixstern", "sonneneinstrahlung", "solarstrahlung"], "d000.s1053.t000": [], "d000.s1055.t000": ["schaft"], "d000.s1056.t000": ["verbalaspekt", "aspekt"], "d000.s1059.t000": ["7-tage-woche", "woche"], "d000.s1064.t000": ["steckdose", "netzsteckdose", "stecker", "wechselstrom-anschluss"], "d000.s1066.t000": ["nehmen", "greifen", "ergreifen", "annehmen", "lesen l\u00e4se"], "d000.s1068.t000": ["stofflich", "materiell", "physisch"], "d000.s1075.t000": ["sammelwerk", "sammlung"], "d000.s1076.t000": ["reduktionsflamme", "feuergarbe", "schach", "flamme", "lohe", "oxidationsflamme", "schachgebot", "feuerzunge", "feuer", "flammen", "flammbrand"], "d000.s1080.t000": ["estragon"], "d000.s1082.t000": ["vollmacht", "mandat", "autorit\u00e4t", "autorisierung", "w\u00e4hlerauftrag", "erm\u00e4chtigung", "autorisiert"], "d000.s1087.t000": ["schnell", "rasch", "geschwind"], "d000.s1089.t000": ["nachkommenschaft", "vererbung", "heredit\u00e4r", "heredit\u00e4t", "abstammung", "vererbungsregel", "erblich"], "d000.s1090.t000": ["nazismus", "nationalsozialismus", "hitlerismus", "nationalsozialist", "nazi"], "d000.s1096.t000": ["brusth\u00f6hle", "brustkasten", "pectus", "brust", "thorax", "oberk\u00f6rper"], "d000.s1098.t000": ["anschauen", "schauen", "sehen", "ansehen", "betrachten", "erblicken"], "d000.s1099.t000": ["kapital", "betriebsnotwendiges kapital", "betriebsverm\u00f6gen", "betriebsnotwendiges verm\u00f6gen", "geldkapital", "betriebskapital"], "d000.s1100.t000": ["mal", "regime"], "d000.s1101.t000": ["christlicher glaube", "christlich", "christliche lehre", "christentum", "christenheit", "christliche religion", "christlicher glauben"], "d000.s1105.t000": ["geheimnis"], "d000.s1107.t000": ["politische militanz", "aktivismus", "aktivist", "aktivistin", "politisches aktivismus"], "d000.s1111.t000": ["schnur", "kordel", "saite"], "d000.s1112.t000": ["shade", "vorhang", "schatten"], "d000.s1116.t000": [], "d000.s1117.t000": ["g\u00e4issbock", "ziegenm\u00e4nnchen", "bock", "ziegenbock", "gei\u00dfbock", "boc"], "d000.s1118.t000": ["sagitta", "pfeil", "sge"], "d000.s1119.t000": ["1000000000000", "preis", "trillion", "gr\u00f6\u00dfe", "billion", "gr\u00f6\u00dfenordnung", "\u00f6konomischer wert", "l-wert", "wert"], "d000.s1120.t000": ["teebl\u00e4tter", "tasse tee", "parametrisierte kurve", "weg", "tee", "teeblatt", "strasse", "stra\u00dfe"], "d000.s1121.t000": ["rechtlicher status", "status", "position"], "d000.s1122.t000": ["neugrad", "winkelgrad", "akademischer grad", "gradma\u00df", "winkelgrade", "diplom", "bogengrad", "altgrad", "grad"], "d000.s1124.t000": ["abc", "alphabet"], "d000.s1128.t000": ["krankheit"], "d000.s1130.t000": ["akku", "taschenleuchte", "sch\u00fctteltaschenlampe", "stablampe", "taschenlampe"], "d000.s1131.t000": [], "d000.s1135.t000": ["trinken", "trinken trinke"], "d000.s1137.t000": ["farbintensit\u00e4t", "unbunte farbe", "bla\u00dfe farbe", "farbs\u00e4ttigung", "s\u00e4ttigung", "farbbrillanz", "graustich", "buntgrad", "farbigkeit", "buntheit", "chromatizit\u00e4t", "bunte farbe"], "d000.s1138.t000": ["winterfett", "lipide", "speicherfett", "subkutanes fettgewebe", "isolierfett", "baufett", "wei\u00dfes fettgewebe", "fett", "k\u00f6rperfett", "fettdepot", "lipid", "fettgewebe"], "d000.s1140.t000": ["blockkommentar", "ideell", "//", "kommentar", "einfallsreichtum", "zeilenkommentar", "idee"], "d000.s1148.t000": ["sprossachse", "rohr", "st\u00e4ngel", "spro\u00dfachse", "stamm", "spross", "apex"], "d000.s1155.t000": ["m\u00e4nnlich", "m\u00e4nner", "m\u00e4nnliches tier", "kerl", "er", "herr", "mannsperson", "mann", "mannsbild", "m\u00e4nnchen", "maskulin", "m\u00e4nnliches geschlecht", "m\u00e4nnlein"], "d000.s1158.t000": ["pappeln", "populus", "pappel"], "d000.s1164.t000": ["orthografie", "schrift", "skriptum", "schreiben", "handschrift", "skript", "rechtschreibung", "orthographisch", "orthographie", "rechtschreibregeln", "schriftsystem"], "d000.s1166.t000": ["dame", "adelige", "edelfrau", "lady"], "d000.s1173.t000": ["lebensalter", "erdjahr", "alter", "ekliptikale l\u00e4nge der sonne", "jahr johr", "erdenjahr", "jahr", "\u00e4ra", "zeitalter", "tropisches jahr"], "d000.s1174.t000": ["fachdisziplin", "unterrichtsfach", "lehrfach", "studienfach", "land", "disziplin", "territorium", "bundesland", "bereich", "provinz", "provinzen", "hoheitsgebiet", "einzelwissenschaft", "schulfach", "fach", "staat", "fachwissenschaft", "feld", "gebiet"], "d000.s1176.t000": ["hinzuf\u00fcgen", "vereinen", "verkn\u00fcpfen", "verbinden", "anschlie\u00dfen", "vereinigen"], "d000.s1178.t000": ["tonwert"], "d000.s1179.t000": ["zur\u00fcckwurf", "zur\u00fcckstrahlen", "echo", "nachhall", "widerhall", "reverb", "widerschein", "widerspiegelung", "zur\u00fcckwerfen", "reverberation"], "d000.s1181.t000": ["distanzfunktion", "pseudometrischer raum", "metrischer raum", "maximum-metrik", "abstandsfunktion"], "d000.s1182.t000": ["rogen"], "d000.s1188.t000": ["rudern"], "d000.s1190.t000": ["kleiden"], "d000.s1194.t000": ["schl\u00fcssel", "r\u00e4ute", "nachschl\u00fcssel"], "d000.s1196.t000": [], "d000.s1198.t000": ["pfandhaus", "pfandleiher", "pfandleiherin"], "d000.s1201.t000": ["passierschein", "stattfinden passiere", "dauerkarte", "zeitkarte", "passieren", "zeitfahrkarte", "geschehen", "sich ereignen"], "d000.s1204.t000": ["abschluss v\u00f6lkerrechtlicher vertr\u00e4ge", "abkommen", "\u00fcbertragungsprotokoll", "protokoll", "v\u00f6lkerrechtliche vertr\u00e4ge", "daten\u00fcbertragungsprotokoll", "netzwerkprotokoll", "netzprotokoll", "internationales \u00fcbereinkommen", "internationale vereinbarung", "v\u00f6lkerrechtsvertrag", "v\u00f6lkervertragsrecht", "vertrag", "internationaler vertrag", "kommunikationsprotokoll", "netzwerk-protokoll", "b\u00fcndnis", "pakt", "v\u00f6lkerrechtlicher vertrag"], "d000.s1206.t000": ["verwandtschaftsverh\u00e4ltnis", "verwandte", "verwandter", "verwandtschaft"], "d000.s1209.t000": ["stammwort", "wurzelwort", "wurzel", "stamm", "wortstamm", "stamm-morphem", "kompositionsstamm", "derivationsstamm"], "d000.s1210.t000": ["konfigurieren"], "d000.s1211.t000": ["tropischer wirbelsturm", "orkan", "hurrikan"], "d000.s1212.t000": ["bibliophilie"], "d000.s1213.t000": ["potentialdifferenz", "anspannung", "elektrisches potential", "elektrische spannung", "spannung"], "d000.s1215.t000": ["anzahl", "ziffer", "zahl", "numerus"], "d000.s1216.t000": ["dichter", "lyriker", "poetin", "dichterin", "versemacher", "poet", "verseschmied"], "d000.s1218.t000": ["ideell", "einfallsreichtum", "ansicht", "idee", "glaube", "annahme", "\u00fcberzeugung", "anschauung", "meinung"], "d000.s1219.t000": ["beif\u00fcgung", "anmerkung", "annotation", "bemerkung", "annotieren"], "d000.s1230.t000": ["bl\u00e4serquartett", "quartett"], "d000.s1232.t000": ["fl\u00fcgel", "tragfl\u00e4che"], "d000.s1236.t000": ["plan", "programmmanagement", "programm"], "d000.s1237.t000": ["kropf", "schilddr\u00fcsenvergr\u00f6\u00dferung", "zungengrundstruma", "satthals", "struma", "struma nodosa"], "d000.s1239.t000": ["speicherabbildungsfunktion", "vektor", "dope-vektor", "arrayelement", "typed array", "feldtyp", "array", "feld"], "d000.s1240.t000": ["zuteilen", "vorbestimmen", "bestimmen", "zuweisen"], "d000.s1242.t000": ["urteilsverm\u00f6gen", "geschmack", "aroma"], "d000.s1244.t000": ["ursus arctos", "kamtschatkab\u00e4r", "brauner karpatenb\u00e4r", "ursus arctos arctos", "europ\u00e4ischer braunb\u00e4r", "braunb\u00e4r"], "d000.s1245.t000": ["stunde", "klasse", "lehrstunde", "lektion", "kurs", "schulstunden", "unterricht", "schulstunde"], "d000.s1248.t000": ["versicherung", "versicherungsprinzip", "versicherungswirtschaft", "assekuranz"], "d000.s1253.t000": ["wortschatz", "vokabular", "lexikon"], "d000.s1255.t000": ["ausf\u00fcllen", "eintragen", "ausf\u00fchren"], "d000.s1256.t000": ["produktionsmechaniker", "zerspanungsmechaniker", "mechaniker", "mechanikerin", "zerspanungsmechanikerin"], "d000.s1257.t000": ["regierungsmannschaft", "kabinett", "gouvernanz", "governance", "lenkungsform", "regierungskabinett", "public governance", "regierung"], "d000.s1259.t000": ["stirn", "dreistigkeit", "unverfrorenheit", "chuzpe", "frechheit"], "d000.s1263.t000": ["kolonien", "pflanzung", "ansiedlung", "niederlassung", "kolonialgebiet", "kolonialregierung", "kolonie", "\u00fcberseebesitzung", "pflanzstadt", "brutkolonie", "siedlung"], "d000.s1267.t000": ["\u00e4gyptische pyramiden", "pyramide"], "d000.s1273.t000": ["schlachtruf", "wahlspruch", "motto", "parole", "werbespr\u00fcche", "devise", "spruch", "slogan", "losung"], "d000.s1275.t000": ["dominion", "dominionstatus", "kolonien", "pflanzung", "kolonialgebiet", "kolonialregierung", "kolonie", "\u00fcberseebesitzung", "pflanzstadt", "brutkolonie"], "d000.s1277.t000": ["tag", "heller tag", "tageszeit", "sonnentag", "tageslicht", "solartag"], "d000.s1278.t000": ["umriss", "rand"], "d000.s1281.t000": ["aussto\u00df"], "d000.s1283.t000": ["mentha", "braune minze", "orangenminze", "basilikumminze", "minzen", "nudelminze", "minze", "zitronenminze", "bergamotteminze"], "d000.s1284.t000": ["tantallampe", "gl\u00fchfadenlampe", "metallfadenlampe", "elektrisches licht", "gl\u00fchlicht", "elektronenr\u00f6hre", "flamme", "feuerzeug", "leuchtmittel", "allgebrauchslampe", "a-lampe", "gl\u00fchlampe", "lampe", "gl\u00fchbirne"], "d000.s1287.t000": [], "d000.s1288.t000": ["biographie", "lebensbeschreibung", "leben", "biografie", "lebende", "lebender"], "d000.s1289.t000": ["http-cookie", "cookie", "http cookie", "tracking cookie", "sitzungscookie", "browser-cookie", "brosame", "kr\u00fcmel", "internet-cookie", "web-cookie", "br\u00f6sel"], "d000.s1290.t000": [], "d000.s1291.t000": ["suchen"], "d000.s1294.t000": ["triebwerk", "motor", "antrieb", "modul"], "d000.s1297.t000": ["krank", "krankheitsrate", "krankheit", "morbidit\u00e4t", "erkrankung", "chranket", "morbidit\u00e4tsrate", "wehleiden", "infektionskrankheit", "gebrechen", "krankheitsverhalten", "erkrankungsrate", "seuche", "gesundheitsst\u00f6rung", "krankheitswert", "krankheitsbild"], "d000.s1298.t000": ["pforte", "tor", "feldeffekttransistor", "t\u00fcren", "t\u00fc\u00fcr", "fet", "t\u00fcre", "gate", "t\u00fcr", "t\u00fcr\u00f6ffnung"], "d000.s1303.t000": ["cicatrix", "narbenbildung", "narbengewebe", "narbe"], "d000.s1306.t000": ["alkohols\u00fcchtiger", "biers\u00e4ufer", "alkoholabh\u00e4ngiger", "alkohols\u00fcchtige", "pietsch", "weins\u00e4uferin", "gewohnheitstrinkerin", "schnapsbruder", "s\u00fcffel", "schluckspecht", "trunkenbold", "saufkumpan", "s\u00e4ufer", "alkoholiker", "besoffene", "zechgenosse", "trunks\u00fcchtiger", "saufkumpanin", "s\u00e4uferin", "weins\u00e4ufer", "alki", "s\u00f6ffel", "zecherin", "trinkerin", "biers\u00e4uferin", "s\u00f6ffer", "alkoholikerin", "gewohnheitstrinker", "saufaus", "trunks\u00fcchtige", "zechgenossin suffkopp", "alkoholkranke", "trinker", "schnapsschwester", "zechbruder", "saufbold", "schnapsdrossel", "zecher", "alkoholkranker", "zechschwester", "besoffener", "besoffski", "s\u00f6fferin"], "d000.s1309.t000": ["lp", "liederalbum", "album", "musikalbum", "platte", "studioalbum"], "d000.s1311.t000": ["episkopos", "eparchie", "episkopat", "bischof", "bisch\u00f6fe", "di\u00f6zese", "sprengel", "kirchensprengel", "bisch\u00f6fin", "bistum", "missionsbischof"], "d000.s1315.t000": [], "d000.s1318.t000": ["element"], "d000.s1321.t000": ["pr\u00e4servativ", "verh\u00fcterli", "\u00fcberzieher", "puderdose", "pr\u00e4ser", "fickt\u00fcte", "gummi", "kondom", "fuffz\u00b4che", "pariser", "nahkampfsocke", "l\u00fcmmelt\u00fcte"], "d000.s1323.t000": ["h\u00f6hepunkt", "b\u00fcrste"], "d000.s1324.t000": ["ufer"], "d000.s1328.t000": ["r\u00fcstung", "fischschuppe", "panzerung", "schuppe"], "d000.s1329.t000": ["anordnung", "gliederung", "beschaffungsauftrag", "normalbestellung", "gerichtsurteil", "bestellung", "bestellnummer", "urteil", "einkaufsauftrag", "einteilung", "bestellanforderung", "purchase order"], "d000.s1331.t000": ["raffgier", "gier", "habsucht gier", "gewinnsucht", "habgier", "raffsucht", "habsucht"], "d000.s1337.t000": ["argumente", "argument", "argumentation", "streitgespr\u00e4ch diskussion", "kontroverse", "argumentum", "streitgespr\u00e4ch", "streit", "argumentieren"], "d000.s1339.t000": ["markt", "weltmarkt", "g\u00fcterm\u00e4rkte", "wochenmarkt", "marktplatz"], "d000.s1340.t000": ["spitze", "webspitze", "kl\u00f6ppelspitze"], "d000.s1344.t000": ["tag", "heller tag", "tageszeit", "tageslicht"], "d000.s1352.t000": ["rassen", "unterart", "rasse", "subspezies"], "d000.s1353.t000": [], "d000.s1354.t000": ["kamm", "hahnenkamm", "h\u00f6hepunkt"], "d000.s1356.t000": ["muriel spark"], "d000.s1358.t000": ["schmuckplatz", "stadtplatz", "platz"], "d000.s1359.t000": ["fest", "sicher"], "d000.s1361.t000": ["felsen", "flueh", "klippe", "kliff", "ufer"], "d000.s1362.t000": ["krise", "psychologische krise", "sinnkrise", "psychische krise", "krisensituation", "lebenskrise"], "d000.s1365.t000": ["zugleich", "zusammen", "zusammen z\u00e4me mitenand"], "d000.s1367.t000": ["finden", "finden aatr\u00e4ffe"], "d000.s1368.t000": ["satzerg\u00e4nzung", "objekt"], "d000.s1369.t000": ["fl\u00fcchtling", "asylbewerber", "asylantin", "gefl\u00fcchteter", "asylbewerberin", "fl\u00fcchtlingin", "fl\u00fcchtlinge", "asylant"], "d000.s1370.t000": ["anweisung", "anordnung", "beschaffungsauftrag", "normalbestellung", "gerichtsurteil", "bestellung", "programmierbefehl", "bestellnummer", "urteil", "einkaufsauftrag", "bestellanforderung", "befehl", "purchase order"], "d000.s1375.t000": ["ausradieren", "l\u00f6schen", "wegwischen", "ausl\u00f6schen"], "d000.s1378.t000": ["porno", "pornografie", "erotika", "porn", "erotik", "geschichte der erotischen darstellung", "nicht jugendfreier inhalt", "erotisch"], "d000.s1379.t000": ["sonne", "prominenter", "star", "stern", "buchstabe", "prominenz", "prominente", "very important person", "ber\u00fchmtheit", "letter", "promi", "fixstern", "prominent"], "d000.s1380.t000": ["dualsystem", "zweiersystem", "bin\u00e4rsystem", "bit"], "d000.s1381.t000": ["\u2764", "herzsymbol", "\u2661", "herzform", "r\u00fchrung", "affektion", "zuneigung", "freundschaftsliebe", "philia", "kern", "streicheleinheit", "herz"], "d000.s1383.t000": ["reich"], "d000.s1385.t000": ["unbeholfen", "unelegant", "ungrazi\u00f6s", "plump", "ungelenk", "klobig", "tollpatschig", "schwerf\u00e4llig", "unansehnlich", "ungeschickt", "unsch\u00f6n"], "d000.s1388.t000": ["ei"], "d000.s1396.t000": ["malfarbe", "lack", "anstrichfarbe", "malerfarbe", "k\u00fcnstlerfarbe", "anstrichstoff", "anstrichmittel", "wandfarbe"], "d000.s1397.t000": ["mikrobielle kultur", "mikroorganismenkultur", "mikrobiologische kultur", "reinkultur"], "d000.s1408.t000": [], "d000.s1410.t000": ["hochchor", "gemischter chor", "altarraum", "obers", "rinde", "presbyterium", "gesangschor", "chor", "gerbrinde", "schale", "gleichstimmiger chor", "robert peel", "sprechchor", "chors\u00e4nger", "mulchrinde", "chorgesang", "borke", "chorraum", "sahne", "rindengewebe", "rahm", "baumrinde", "chorquadrat", "chorist", "volkschor", "ttbb"], "d000.s1415.t000": ["minorennit\u00e4t", "unter 18", "halbstarker", "bube", "jugendliche", "minderj\u00e4hrige", "minderj\u00e4hriger", "bursche", "minderj\u00e4hrigkeit", "minderj\u00e4hrig", "kind"], "d000.s1419.t000": ["pfund", "pound sterling", "ukp", "\u2114", "zollpfund", "british pound", "gbp", "englisches pfund", "britische pfund", "britisches pfund", "pfund sterling", "schottische pfund"], "d000.s1423.t000": ["lenticelle", "leonis", "l\u00f6we", "korkwarze", "lentizelle", "\u264c", "korkpore", "lentizellen", "leo"], "d000.s1424.t000": ["massenverkehrssystem", "massenverkehr", "verkehr", "bef\u00f6rderungsmittel", "\u00f6ffentlicher personenverkehr", "transport zu lande", "datentransport", "\u00f6ffentlicher verkehr", "transit", "verkehrsbelastung", "transportmittel", "warenbef\u00f6rderung", "transportwesen", "\u00f6ffentliche verkehrsmittel", "transport", "\u00f6ffis", "personenverkehr"], "d000.s1426.t000": ["tierart", "sorte", "species", "spezies", "art"], "d000.s1427.t000": ["kops", "induktivit\u00e4t", "ein halb", "rolle", "1/2", "spule", "induktanz", "h\u00e4lfte", "0,5"], "d000.s1430.t000": ["halbh\u00f6hle", "gletscherh\u00f6hle", "h\u00f6hle", "naturh\u00f6hle"], "d000.s1433.t000": ["pr\u00e4servativ", "verh\u00fcterli", "\u00fcberzieher", "puderdose", "pr\u00e4ser", "fickt\u00fcte", "gummi", "kondom", "fuffz\u00b4che", "pariser", "nahkampfsocke", "l\u00fcmmelt\u00fcte"], "d000.s1435.t000": ["menschlichkeit", "humanit\u00e4t"], "d000.s1436.t000": ["hofn\u00e4rrin", "narr", "hofnarr", "n\u00e4rrin"], "d000.s1437.t000": ["mythographie", "mythologie", "mythograph", "mythograf"], "d000.s1438.t000": ["stummel", "zigarette", "zigarettenkippe", "cigarette", "kippe", "zigarettenstummel"], "d000.s1442.t000": ["ofen", "r\u00e9chaud", "rechaud", "warmhalteplatte", "gasherd"], "d000.s1443.t000": ["sprechen", "gesprochene sprache", "m\u00fcndliche kommunikation", "sprache", "gesprochenes", "zunge"], "d000.s1445.t000": ["zeitform", "zeitformen", "zeitraum", "periode", "epoche", "\u00e4ra", "zeitalter", "tempora", "zeit", "deutsche tempusformen", "tempus"], "d000.s1446.t000": ["deuten", "zeigen"], "d000.s1454.t000": ["paillette"], "d000.s1464.t000": ["kohle", "knete"], "d000.s1465.t000": ["ass"], "d000.s1473.t000": ["stumpf", "abgestumpft"], "d000.s1474.t000": ["volk", "leute", "nationalit\u00e4t"], "d000.s1475.t000": ["ort", "platz", "geographische lage", "stelle", "merlefaktor", "position", "merle-faktor", "koordinate", "fleck", "standort", "stellung"], "d000.s1477.t000": [], "d000.s1480.t000": ["board of directors", "verwaltungsorgan", "f\u00fchrungslinie"], "d000.s1482.t000": ["kontor", "bureau", "koryph\u00e4e", "autorit\u00e4t", "b\u00fcro", "demonstration von autorit\u00e4t", "verwaltungsbeh\u00f6rde", "beh\u00f6rde", "regierungsbeh\u00f6rde", "oberbeh\u00f6rde", "amt"], "d000.s1483.t000": ["rasenfl\u00e4che", "rasen", "wiese"], "d000.s1487.t000": ["domestiziertes tier"], "d000.s1489.t000": ["pr\u00e4zisionssch\u00fctze", "heckensch\u00fctze", "scharfsch\u00fctze", "scharfsch\u00fctzen", "scharfsch\u00fctzin", "heckensch\u00fctzin"], "d000.s1491.t000": ["betonen", "gewichtung", "emphase", "betonung", "akzent"], "d000.s1492.t000": ["ausnahme", "auslassung"], "d000.s1493.t000": ["samen", "ejakulat", "saat", "sperma", "samenfl\u00fcssigkeit", "same", "pflanzensamen", "s\u00e4merei", "wichse", "samenkorn"], "d000.s1494.t000": [], "d000.s1500.t000": ["entfernung", "l\u00e4ngenma\u00df", "distanz", "abstand", "l\u00e4nge", "abstandsma\u00df"], "d000.s1501.t000": [], "d000.s1502.t000": ["zollgeb\u00fchren", "zollamt", "zoll", "zollhaus"], "d000.s1505.t000": ["hauszwiebel", "zwiebellauch", "zwiebel", "zwiebeln", "gartenzwiebel", "luftzwiebel", "etagenzwiebel", "gemeine zwiebel", "allium cepa", "sommerzwiebel", "zwiebelpflanze", "k\u00fcchenzwiebel", "speisezwiebel", "blumenzwiebel"], "d000.s1506.t000": ["rohbau", "rahmen", "fahrgestell"], "d000.s1507.t000": ["abbrechen", "r\u00fcckg\u00e4ngig machen", "ungeschehen machen", "auswahl aufheben"], "d000.s1516.t000": ["antlitz", "gesicht", "konterfei", "angesicht", "visage"], "d000.s1519.t000": ["kleinstadt", "gro\u00dfstadt", "metropole", "stadt"], "d000.s1521.t000": ["gravidit\u00e4t", "gestation", "schwangerschaft", "tragzeit", "tragezeit"], "d000.s1523.t000": ["chorfrau", "krankenpfleger", "mutter", "pfleger", "klosterschwester", "krankenpflegerin", "nonne", "ordensschwester", "mama", "pflegerin", "krankenschwester", "schwester"], "d000.s1524.t000": ["maximum", "extremum", "extremwert", "lokales maximum", "lokales minimum"], "d000.s1525.t000": ["set", "satz", "menge"], "d000.s1527.t000": ["doofkopf", "idiot", "bl\u00f6dian", "dumpfbacke", "schwachmat", "dummbratze", "strohkopf", "schwachkopf", "kamel", "einfaltspinsel", "tor", "dummkopf", "holzkopf", "spatzengehirn", "tropf", "dumme gans", "spaten", "l\u00f6\u00f6l", "doofi", "n\u00e4rrin", "hohlkopf", "dummerjan", "d\u00f6skopp", "schafskopf", "honk", "depp", "t\u00f6rin", "hirni", "mondkalb", "armleuchter", "flachwichser", "hornochse", "stiesel", "hofn\u00e4rrin", "dummer mensch", "spatzenhirn", "gimpel", "trottel", "dummerchen", "simpel", "bl\u00f6dmann", "kindskopf", "rindvieh", "narr", "vollpfosten", "vollhonk", "d\u00e4mlack", "esel", "ein dummer mensch", "hofnarr"], "d000.s1533.t000": ["rand", "k\u00fcstenabschnitt", "k\u00fcste", "meeresk\u00fcste", "s\u00fcdafrikanischer rand", "strand", "gew\u00e4sserrandstreifen", "uferbereich", "flussufer", "uferb\u00f6schung", "buchtenk\u00fcste", "k\u00fcstenform", "zar", "ufergegend", "au\u00dfenuferzone", "ufergeh\u00f6lzzone", "ufer", "k\u00fcstenland", "uferstreifen"], "d000.s1535.t000": ["erreichen", "ankommen", "gelangen", "kommen"], "d000.s1541.t000": ["queckenwurzel", "hystrix", "haargerste", "quecken", "elymus"], "d000.s1542.t000": ["rufaufbau", "anruf", "telefongespr\u00e4ch", "sprachanruf", "sprachkanal", "rede", "ansprache", "telefonat", "gespr\u00e4ch", "telefonverbindung", "vortrag", "telefonanruf", "w\u00e4hltasten"], "d000.s1550.t000": ["not"], "d000.s1555.t000": ["koppeln", "link", "verkn\u00fcpfen", "zuordnen"], "d000.s1557.t000": ["schule", "akademie", "hochschule", "lehranstalt", "bildungsanstalt", "universit\u00e4t", "uni"], "d000.s1558.t000": ["herunterladen", "verl\u00e4ngern", "ziehen", "sich spannen", "spannen", "downloaden", "reichen"], "d000.s1559.t000": ["selektive stabilisierung", "nat\u00fcrliche zuchtwahl", "selektive retention", "survival of the fittest", "selektive stabilisation", "nat\u00fcrliche auslese", "auswahl", "selektion", "\u00fcberleben der bestangepassten"], "d000.s1563.t000": ["schwimmdock", "dock"], "d000.s1565.t000": [], "d000.s1566.t000": ["gericht", "teller", "platte", "speise", "sch\u00fcssel"], "d000.s1567.t000": ["zunft", "z\u00fcnfte", "handwerksgilde", "z\u00fcnften", "gilde", "verbindung", "gesellschaft", "klub", "bruderschaft", "vereinigung", "handwerkszunft", "orden", "freiwillige vereinigung", "innung", "allianz", "verband", "zunftwesen", "verein"], "d000.s1569.t000": ["hinterarm", "arms", "freie obere extremit\u00e4t", "arm", "hand", "brachium", "oberarm", "h\u00e4nde"], "d000.s1575.t000": ["tor", "goal"], "d000.s1577.t000": ["band", "buchgestaltung"], "d000.s1580.t000": [], "d000.s1581.t000": ["erinaceus", "kleinohrigel"], "d000.s1582.t000": ["silberleinwand", "videoleinwand", "projektionswand", "bildschirm", "bildwand"], "d000.s1585.t000": ["orthografie", "schrift", "skriptum", "schreiben", "handschrift", "skript", "rechtschreibung", "orthographisch", "orthographie", "rechtschreibregeln", "schriftsystem"], "d000.s1587.t000": ["auswirkung", "effekt", "aktivit\u00e4t", "konsequenz", "wirkung", "ergebnis", "wirkungsintegral", "folge", "physikalische wirkung", "resultat"], "d000.s1593.t000": ["monopol", "monopoly"], "d000.s1602.t000": ["papiersack", "papiert\u00fcte", "sack", "traget\u00fcte", "tragetasche", "sackerl", "plastikt\u00fcte", "tasche", "beutel", "t\u00fcte"], "d000.s1605.t000": ["sprechen", "einzelsprachlich", "einzelsprache", "gesprochene sprache", "m\u00fcndliche kommunikation", "menschliche sprache", "sprache", "gesprochenes", "zunge"], "d000.s1606.t000": ["krise", "notlage"], "d000.s1609.t000": ["statistik", "statistische analyse"], "d000.s1614.t000": ["geburt", "entbindung", "niederkunft", "weihnachtsgeschichte", "kindsgeburt"], "d000.s1616.t000": ["diagnose"], "d000.s1617.t000": ["panzerkassa", "safe", "wertschutzschrank", "tresor", "wertschrank", "panzerschrank", "geldschrank"], "d000.s1628.t000": ["sto\u00dfen auf", "anschauen", "schauen", "sehen", "ansehen", "antreffen", "begegnen", "treffen", "betrachten", "erblicken"], "d000.s1631.t000": ["zuh\u00f6ren zuelose", "h\u00f6ren", "beachten", "zuh\u00f6ren", "aufpassen"], "d000.s1633.t000": ["pforte", "tor", "feldeffekttransistor", "t\u00fcren", "t\u00fc\u00fcr", "fet", "t\u00fcre", "gate", "t\u00fcr", "t\u00fcr\u00f6ffnung"], "d000.s1638.t000": ["leistung", "st\u00e4rke", "kraft"], "d000.s1639.t000": ["corydalis", "lerchensporn", "lerchensporne"], "d000.s1641.t000": ["komponente", "bauteil", "einzelteil"], "d000.s1642.t000": ["sein", "sein sich befinden", "passieren", "sein stattfinden", "bestehen", "existieren", "geschehen"], "d000.s1644.t000": ["vorstellen", "sich vorstellen", "sinnieren", "nachdenken", "\u00fcberlegen", "reflektieren", "einbilden", "nachsinnen", "denken", "gr\u00fcbeln", "sinnen"], "d000.s1646.t000": ["milchmix", "milchmixgetr\u00e4nk", "milkshake", "fruchtshake", "milchmischgetr\u00e4nk", "milchshake"], "d000.s1648.t000": ["pforte", "tor", "feldeffekttransistor", "eingangst\u00fcr", "fet", "t\u00fcrfutter", "t\u00fcre", "gate", "t\u00fcr", "t\u00fcrrahmen", "t\u00fcrzarge"], "d000.s1654.t000": ["ja!", "lebensalter", "erdjahr", "alter", "ekliptikale l\u00e4nge der sonne", "erdenjahr", "jahr", "\u00e4ra", "zeitalter", "tropisches jahr"], "d000.s1655.t000": ["beispiel", "modell", "exempel", "exemplar", "konzeptionelles modell", "konzeptmodell"], "d000.s1656.t000": ["heilige", "nationalheiliger", "heiliger"], "d000.s1657.t000": ["demagoge", "volksverf\u00fchrung", "demagogie"], "d000.s1659.t000": ["pionier", "private first class", "private", "panzerfunker", "sanit\u00e4tssoldat", "panzerpionier", "soldatin", "flieger", "funker", "panzersoldat", "soldat"], "d000.s1662.t000": ["kohldampf", "hungergef\u00fchl", "hungerzentrum", "hungern", "welthunger", "hunger"], "d000.s1663.t000": [], "d000.s1665.t000": ["bezahlung", "zahlung"], "d000.s1666.t000": ["gef\u00e4lle", "steigungswinkel", "anstieg", "steigung", "ableitung", "gradient", "neigung"], "d000.s1667.t000": ["herbstsemester", "vorlesungszeit", "herbst-winter-semester", "sommersemester", "wintersemester", "prosemester", "wise", "semester", "fachsemester", "sose"], "d000.s1670.t000": ["tastatur", "keyboard", "gebrochene oktave", "kurze oktave", "klaviertastatur", "tasteninstrument", "manual", "klaviatur", "computertastatur", "manuale"], "d000.s1671.t000": ["pest", "agrarsch\u00e4dling", "sch\u00e4dling", "pestilenz", "schadinsekt", "bubonenpest", "sch\u00e4dlinge", "seuche", "pestsepsis"], "d000.s1674.t000": ["magma"], "d000.s1677.t000": ["\u00e4igeschaft", "eigenschaft", "qualit\u00e4t"], "d000.s1678.t000": ["schwer"], "d000.s1680.t000": ["alkalien", "base", "basen", "alkalie"], "d000.s1681.t000": ["erektionsschw\u00e4che", "potenzschw\u00e4che", "impotentia coeundi", "erektionsschwierigkeiten", "potenzst\u00f6rung", "potentia coeundi", "impotent", "mannesschw\u00e4che", "erektile dysfunktion", "erektionsst\u00f6rung", "ed", "impotenz"], "d000.s1683.t000": ["anweisung", "anordnung", "befehl", "programmierbefehl", "haftzeit"], "d000.s1689.t000": ["wasserlauf", "bachlauf", "bach", "mittelgebirgsbach", "flachlandbach", "gebirgsbach", "flie\u00dfgew\u00e4sser"], "d000.s1691.t000": ["rotfuchs", "f\u00fcchslein", "vulpes vulpes", "fuchs", "vul", "vulpecula", "vulpes"], "d000.s1692.t000": ["liebesspiel", "stock", "paarung", "kopulation", "verkehr", "koitus", "geschlechtsverkehr", "sexualkontakt", "geschlechtsakt", "akt", "kohabitation", "beischlaf", "sex", "begattung", "liebesakt"], "d000.s1693.t000": ["b\u00fcrgerschaft", "nationalit\u00e4t"], "d000.s1694.t000": ["job", "unternehmen", "beruf", "stelle", "einzelvorgang", "t\u00e4tigkeit", "erwerbst\u00e4tigkeit", "besch\u00e4ftigung", "gesch\u00e4ft", "anstellung", "arbeit"], "d000.s1695.t000": ["originalit\u00e4t"], "d000.s1700.t000": ["anfangen", "starten", "beginnen"], "d000.s1706.t000": ["kraft"], "d000.s1713.t000": ["\u00e4igeschaft", "eigenschaft", "attribut", "qualit\u00e4t"], "d000.s1716.t000": ["insurrektion", "insurgency", "rebellion", "insurgent", "aufruhr", "insurgenten", "insurrektionskrieg", "aufstand", "insurgenz"], "d000.s1717.t000": ["pferdeevolution", "gaul", "equiden", "pferde", "equus", "ross", "hotteh\u00fc", "urpferd", "einhufer", "pferd", "hauspferd"], "d000.s1718.t000": ["glas"], "d000.s1734.t000": ["zypressen", "zypresse", "cupressus"], "d000.s1736.t000": ["album"], "d000.s1741.t000": ["einflussbereich", "einflussgebiet", "wirkungsbereich", "einflusssph\u00e4re", "geltungsbereich", "herrschaftsbereich", "machtbereich", "stimmlage", "bereich"], "d000.s1746.t000": ["riebli", "gelber\u00fcbe", "karotte", "m\u00f6hre", "wurzel", "r\u00fcebli", "gelbe r\u00fcbe", "mohrr\u00fcbe", "gelbr\u00fcbe", "daucus carota subsp. gummifer"], "d000.s1748.t000": ["fremdenf\u00fchrerin", "reiseleiterin", "fremdenf\u00fchrer", "reiseleiter", "reisef\u00fchrer"], "d000.s1749.t000": ["seminar", "seminare"], "d000.s1753.t000": ["tanz"], "d000.s1754.t000": ["clientcomputer", "klient", "client", "clientanwendung", "clientsoftware", "knoten"], "d000.s1756.t000": ["schriftsystem", "brief", "orthografie", "schrift", "skriptum", "papierbrief", "schreiben", "orthographie", "skript", "rechtschreibung", "orthographisch", "sendschreiben", "musterbrief", "rechtschreibregeln", "briefkopf"], "d000.s1758.t000": ["moose", "moos", "moospflanzen", "bryophyten", "moospflanze"], "d000.s1762.t000": ["zulassen", "erlauben"], "d000.s1765.t000": ["l\u00e4utemaschine", "glockengie\u00dfen", "glockenspeise", "armbanduhren", "armband-uhren", "glockengu\u00df", "kirchenglocke", "uhr", "gu\u00dfstahlglocke", "armbanduhr", "glockengiessen", "einsatzuhr", "l\u00e4uteanlage", "glocke", "armband-uhr"], "d000.s1770.t000": ["altar", "ara"], "d000.s1773.t000": ["tag", "heller tag", "tageszeit", "sonnentag", "tageslicht", "solartag"], "d000.s1776.t000": [], "d000.s1780.t000": ["sehr schlecht", "miserabel"], "d000.s1784.t000": ["fechtsport", "fechten", "sportfechten"], "d000.s1787.t000": [], "d000.s1788.t000": ["plan", "landkarte", "karte"], "d000.s1790.t000": ["schwertlilie", "schwertlilien", "iris"], "d000.s1792.t000": ["beabsichtigen", "sinnieren", "intendieren", "vorhaben", "nachdenken", "\u00fcberlegen", "reflektieren", "nachsinnen", "denken", "gr\u00fcbeln", "sinnen"], "d000.s1796.t000": ["taburett", "schemel", "hocker"], "d000.s1799.t000": ["vehikel", "fahrzeug", "landfahrzeug"], "d000.s1804.t000": ["zahlungsmittel", "kohle", "knete", "geld", "zaster", "schotter", "moneten"], "d000.s1805.t000": ["schwierigkeit", "probleme", "problem", "problematisch", "problematik", "problemkl\u00e4rung"], "d000.s1807.t000": ["\u2295", "boden", "sol iii", "blauer planet", "erde", "\u2641", "bundesstaat in mexiko", "l\u00e4nder", "land der bundesrepublik deutschland", "grund", "land", "erdboden", "bundesland", "erdkugel", "sol 3", "nationalstaat", "erdk\u00f6rper", "festland", "nation", "staat", "weltkugel", "verwaltungseinheit von mexiko", "welt"], "d000.s1809.t000": ["zeitform", "absolute zeit", "zeitformen", "nunc stans", "zeitintervall", "tempora", "physikalische zeit", "zeit", "deutsche tempusformen", "tempus"], "d000.s1811.t000": ["passierschein", "stattfinden passiere", "dauerkarte", "zeitkarte", "passieren", "zeitfahrkarte", "geschehen", "sich ereignen"], "d000.s1812.t000": ["machandelbaum", "gemeiner wacholder", "heide-wacholder", "juniperus communis"], "d000.s1814.t000": ["klage", "rechtssache", "wirkungskette", "monokausal", "antrag", "kausalgesetz", "kausalnexus", "multikausalit\u00e4t", "kausalzusammenhang", "prozess", "kausalit\u00e4t", "prinzip von ursache und wirkung", "kausalit\u00e4tskette", "antezendenz", "chlegti", "rechtsstreit", "rechtsfall", "kausalbeziehung", "ursache-wirkung", "kausalordnung", "kausal", "kausaler zusammenhang", "urs\u00e4chlichkeit", "multikausal", "fall", "gerichtsverfahren", "gerichtsfall"], "d000.s1815.t000": ["pension", "gasthaus", "g\u00e4stehaus"], "d000.s1817.t000": ["sternbild hase", "hase", "lepus", "echte hasen"], "d000.s1820.t000": ["aktivierung"], "d000.s1821.t000": ["merken"], "d000.s1827.t000": ["blumenerde", "bodenbeschaffenheit", "boden", "erdreich", "erde", "schmodder", "dreck", "schmutz", "grund", "fleck", "erde schmutz"], "d000.s1828.t000": ["finden", "finden aatr\u00e4ffe"], "d000.s1829.t000": ["quell", "quelle", "wasserquelle"], "d000.s1835.t000": ["atlantischer hering", "echte heringe"], "d000.s1836.t000": [], "d000.s1838.t000": ["ehegatte", "m\u00e4nnlich", "gemahl", "m\u00e4nnliches tier", "ehegemahl", "ehegespons", "er", "herr", "mann", "ehegesponst", "gatte", "ehepartner", "ehemann", "m\u00e4nnchen", "maskulin", "m\u00e4nnliches geschlecht", "m\u00e4nnlein"], "d000.s1839.t000": ["gg", "teratonne", "kt", "t", "megagramm", "petatonne", "metrische tonne", "tonne", "kilotonne", "mg"], "d000.s1840.t000": ["finanzierung", "geldmittel", "finanzen"], "d000.s1841.t000": ["unternehmensf\u00fchrung", "general management", "verwaltungsorgan", "verwaltung", "verabreichung", "manager", "bwl", "f\u00fchrung", "verwaltungsbeh\u00f6rde", "betriebs\u00f6konomie", "betriebswirtschaftslehre", "management", "administration"], "d000.s1842.t000": ["vogelpenis", "schwanz", "pimmel", "mitglied", "m\u00e4nnliches glied", "l\u00fcmmel", "pipimann", "ger\u00e4t", "penis", "arsch", "zipfel", "corpus penis", "piepmatz", "teil", "penis der v\u00f6gel", "glied", "willy", "penisschaft", "penis der s\u00e4ugetiere"], "d000.s1854.t000": ["hexaeder", "kubus", "w\u00fcrfel", "gleichseitiger hexaeder"], "d000.s1855.t000": ["tierwelt", "fauna", "tierleben", "metazoa", "tier", "animalia", "tierreich", "bestie", "tierfortpflanzung"], "d000.s1856.t000": ["greifschwanz", "wickelschwanz", "schwanz", "cauda", "rute", "saba", "isla de san crist\u00f3bal", "b\u00fcrzel", "isla de san cristobal", "zagel", "schweif", "schw\u00e4nzlein", "stert", "schw\u00e4nzchen", "sterz"], "d000.s1860.t000": ["ernennen", "schlafen", "nageln", "poppen", "in die kiste springen", "liebe machen", "miteinander schlafen", "zuweisen", "kn\u00e4ggern", "v\u00f6geln", "es tun", "pudern", "rammeln", "sex haben", "verpflichten", "knallen", "sto\u00dfen", "einen wegstecken", "sich dem liebesspiel hingeben", "anweisen", "koitieren", "eros opfern", "sich der sch\u00f6nsten nebensache der welt widmen", "in die kissen steigen", "schnackseln", "stechen", "ficken", "es treiben", "bumsen", "r\u00f6deln", "erkennen", "beauftragen", "geschlechtsverkehr haben", "pimpern"], "d000.s1864.t000": ["einbuchtung"], "d000.s1865.t000": ["geschmacksinn", "schmecken", "geschmackswahrnehmung", "gust", "gustatorische wahrnehmung", "geschmacksempfindung", "geschmacksrichtung", "geschmack", "gustatorik", "aroma", "geschmackssinn", "gustatorisch"], "d000.s1867.t000": ["schaden"], "d000.s1873.t000": ["wahrnehmen"], "d000.s1874.t000": ["maulwurf", "sch\u00ebre"], "d000.s1877.t000": ["gefrorener tau", "tau", "weisser tau", "tauperle"], "d000.s1879.t000": ["\u2640", "weib", "feminin", "ehepartnerin", "ehegattin", "ehegespons", "weibsperson", "eheweib", "dame", "frauenzimmer", "ehegesponst", "gemahlin", "weibliches geschlecht", "ehefrau", "frau", "gattin"], "d000.s1880.t000": ["geben", "\u00fcberreichen", "aush\u00e4ndigen", "reichen", "abgeben"], "d000.s1884.t000": ["ungebunden", "frei"], "d000.s1891.t000": ["einbruchdiebstahl", "hausfriedensbruch", "einbruch", "bruch"], "d000.s1894.t000": ["intonation"], "d000.s1899.t000": ["schloss", "palast"], "d000.s1900.t000": ["laufsport", "laufen", "dauerlauf"], "d000.s1903.t000": ["ankommen", "kommen"], "d000.s1906.t000": ["diskus", "laufwerksbuchstabe", "disc", "laufwerk", "datentr\u00e4ger", "speicherlaufwerk"], "d000.s1907.t000": ["logische partition", "erweiterte partition", "logisches ger\u00e4t", "logisches laufwerk", "logischer datentr\u00e4ger", "datentr\u00e4gerpartition", "prim\u00e4re partition", "partition"], "d000.s1912.t000": ["papa", "vater"], "d000.s1917.t000": ["haubitze", "panzerhaubitze", "howitzer", "feldhaubitze", "m\u00f6rser"], "d000.s1920.t000": ["1000000000000", "soziale werte", "preis", "wertesystem", "trillion", "\u00f6konomischer wert", "wertevorstellung", "wichtigkeit", "gr\u00f6\u00dfenordnung", "gr\u00f6\u00dfe", "billion", "wertvorstellung", "werte", "ethische grundprinzipien", "l-wert", "wert"], "d000.s1929.t000": [], "d000.s1932.t000": ["aussehen"], "d000.s1938.t000": ["papa", "vater"], "d000.s1940.t000": ["f\u00fcrstentum andorra", "andorra"], "d000.s1942.t000": ["rohbau", "rahmen", "fahrgestell"], "d000.s1951.t000": ["basis", "basisvektor", "hamelbasis", "hamelsche basis", "basisfunktion", "basiserg\u00e4nzungssatz", "vektorraumbasis"], "d000.s1952.t000": ["wasser", "h\u2082o", "h2o"], "d000.s1954.t000": ["schiffshinterteil", "hinterschiff", "heck"], "d000.s1958.t000": ["\u00fcberraschung"], "d000.s1962.t000": ["eigentliche enten", "eigentliche schwimmenten"], "d000.s1963.t000": ["benehmen", "verhalten"], "d000.s1966.t000": [], "d000.s1971.t000": ["charakter", "lektion", "lehre"], "d000.s1975.t000": ["futter", "pferdefutter", "fruchtwechselfolge", "viehfutter", "futtermittel", "felderwirtschaft", "landwechsel", "hauptfrucht", "vierfelderwirtschaft", "fourage", "brachland", "fruchtwechselwirtschaft", "zweifelderwirtschaft", "fruchtfolge", "tiernahrung", "brache"], "d000.s1977.t000": ["nasenpopel", "brustschwimmen", "rotz", "schleim", "popel", "brust"], "d000.s1979.t000": ["kommunistin", "kommunist", "kommunismus"], "d000.s1980.t000": ["programmation en logique", "prolog"], "d000.s1990.t000": ["verhindern", "vorbeugen"], "d000.s1992.t000": ["schn\u00fcrenpudel", "zwergpudel", "pudel", "gro\u00dfpudel", "k\u00f6nigspudel", "kleinpudel", "caniche"], "d000.s1993.t000": ["baustoffwechsel", "anaboler stoffwechsel", "anabolisch", "anabolismus"]}